{
  "placeholderImages": [
    {
      "id": "app-logo",
      "description": "Logotipo oficial de ColserDev",
      "imageUrl": "/Logo.png",
      "imageHint": "company logo"
    },
    {
      "id": "hero-mockup",
      "description": "Mockup de software premium de ColserDev",
      "imageUrl": "/images/banner.png",
      "imageHint": "software dashboard interface"
    },
    {
      "id": "service-web",
      "description": "Desarrollo web moderno con Next.js",
      "imageUrl": "/images/servicios/Diseño_web.jpg",
      "imageHint": "web design"
    },
    {
      "id": "service-mobile",
      "description": "Apps móviles nativas y multiplataforma",
      "imageUrl": "/images/servicios/app_movil.jpg",
      "imageHint": "mobile application development"
    },
    {
      "id": "service-cloud",
      "description": "Infraestructura en la nube",
      "imageUrl": "https://picsum.photos/seed/service-cloud-dev/600/400",
      "imageHint": "cloud server technology"
    },
    {
      "id": "service-custom",
      "description": "Desarrollo de software a la medida para empresas",
      "imageUrl": "https://picsum.photos/seed/service-custom-software/600/400",
      "imageHint": "software engineering code"
    },
    {
      "id": "project-1",
      "description": "Dashboard de Fintech",
      "imageUrl": "https://picsum.photos/seed/project-fintech/800/600",
      "imageHint": "financial dashboard ui"
    },
    {
      "id": "project-2",
      "description": "Plataforma E-commerce",
      "imageUrl": "https://picsum.photos/seed/project-ecommerce/800/600",
      "imageHint": "online shopping platform"
    },
    {
      "id": "project-3",
      "description": "Monitor de Salud VitalTrack",
      "imageUrl": "https://picsum.photos/seed/project-health/800/600",
      "imageHint": "medical health app"
    },
    {
      "id": "avatar-1",
      "description": "Retrato de Sarah Johnson",
      "imageUrl": "https://picsum.photos/seed/sarah-j/100/100",
      "imageHint": "professional woman"
    },
    {
      "id": "avatar-2",
      "description": "Retrato de Michael Chen",
      "imageUrl": "https://picsum.photos/seed/michael-c/100/100",
      "imageHint": "business man portrait"
    },
    {
      "id": "avatar-3",
      "description": "Retrato de Elena Rodriguez",
      "imageUrl": "https://picsum.photos/seed/elena-r/100/100",
      "imageHint": "latina entrepreneur"
    }
  ]
}